pycountskhb/__init__.py
pycountskhb/plotting.py
pycountskhb/pycountskhb.py
pycountskhb-0.1.0.dist-info/LICENSE
pycountskhb-0.1.0.dist-info/WHEEL
pycountskhb-0.1.0.dist-info/METADATA
pycountskhb-0.1.0.dist-info/RECORD
